{
  "manifestVersion": 1,
  "id": "worklog-extension",
  "version": "1.0.0",
  "name": "Worklog Extension",
  "publisher": "RobinWessel",
  "targets": [
    {
      "id": "Microsoft.VisualStudio.Services"
    }
  ],
  "description": "Logge Arbeitszeit in Stunden und Minuten direkt im Work Item. Hält die Gesamtsumme im Feld und schreibt Sessions in die History.",
  "categories": [
    "Azure Boards"
  ],
  "scopes": [
    "vso.work_write"
  ],
  "contributions": [
    {
      "id": "worklog-control",
      "type": "ms.vss-work-web.work-item-form-control",
      "targets": [
        "ms.vss-work-web.work-item-form"
      ],
      "properties": {
        "name": "Worklog Control",
        "uri": "dist/index.html",
        "height": 140
      }
    }
  ],
  "files": [
    {
      "path": "dist",
      "addressable": true
    }
  ]
}